vutwifi.py
vutwifi/__init__.py
vutwifi/__main__.py
vutwifi/vutwifi.py
vutwifi-0.3.2.dist-info/METADATA
vutwifi-0.3.2.dist-info/WHEEL
vutwifi-0.3.2.dist-info/entry_points.txt
vutwifi-0.3.2.dist-info/top_level.txt
vutwifi-0.3.2.dist-info/RECORD
