Metadata-Version: 2.1
Name: vutwifi
Version: 0.3.2
Summary: Connect to the WIFI at FIT VUT in Brno.
Home-page: https://github.com/luminaar/vutwifi
Author: Thomas Levine, Max K. Luminar
Author-email: kovykmax@gmail.com
License: AGPL
Platform: UNKNOWN
Classifier: Programming Language :: Python :: 3.5
Classifier: Programming Language :: Python :: 3.6
Classifier: Programming Language :: Python :: 3.7
Classifier: Programming Language :: Python :: 3.8
Requires-Dist: requests (<3.0,>=2.22)
Requires-Dist: click (<8.0,>=7.0)
